libgcs/__init__.py
libgcs/file.py
libgcs/preference_tools.py
libgcs/queue.py
libgcs/serial_tools.py
libgcs/_base/__init__.py
libgcs/_base/exception.py
libgcs/_base/gcs_program.py
libgcs/_base/logger.py
libgcs/_base/preference_loader.py
libgcs/_base/preference_tree.py
libgcs/_base/threading.py
libgcs-1.0.4.dist-info/METADATA
libgcs-1.0.4.dist-info/WHEEL
libgcs-1.0.4.dist-info/entry_points.txt
libgcs-1.0.4.dist-info/RECORD
